ccb/__init__.py
ccb/archive_handler.py
ccb/cli.py
ccb/converter.py
ccb/exceptions.py
ccb/file_detector.py
ccb/utils.py
ccb_cli-2.2.0.dist-info/METADATA
ccb_cli-2.2.0.dist-info/WHEEL
ccb_cli-2.2.0.dist-info/entry_points.txt
ccb_cli-2.2.0.dist-info/RECORD
