Metadata-Version: 2.4
Name: ccb-cli
Version: 2.2.0
Summary: Convert to Comic Book - 将图片文件夹或压缩包转换为漫画书格式
Project-URL: Homepage, https://github.com/kongolou
Project-URL: Documentation, https://kongolou.github.io/convert-to-comic-book/
Project-URL: Repository, https://github.com/kongolou/convert-to-comic-book.git
Project-URL: Issues, https://github.com/kongolou/convert-to-comic-book/issues
Project-URL: Changelog, https://github.com/kongolou/convert-to-comic-book/blob/main/CHANGELOG.md
Author-email: kongolou <kongolou@163.com>
Maintainer-email: kongolou <kongolou@163.com>
License-Expression: MIT
Keywords: Comic,漫画
Classifier: Programming Language :: Python :: 3.10
Classifier: Programming Language :: Python :: 3.11
Classifier: Programming Language :: Python :: 3.12
Classifier: Programming Language :: Python :: 3.13
Classifier: Programming Language :: Python :: 3.14
Requires-Python: >=3.10
Provides-Extra: dev
Requires-Dist: coverage>=7.13.1; extra == 'dev'
Requires-Dist: pytest-cov>=7.0.0; extra == 'dev'
Requires-Dist: pytest>=9.0.2; extra == 'dev'
Provides-Extra: docs
Requires-Dist: mkdocs-material>=9.0.0; extra == 'docs'
Requires-Dist: mkdocs>=1.5.0; extra == 'docs'
Requires-Dist: mkdocstrings[python]>=0.24.0; extra == 'docs'
Provides-Extra: full
Requires-Dist: py7zr>=0.21.0; extra == 'full'
Requires-Dist: rarfile>=4.0; extra == 'full'
Provides-Extra: standard
